sharp/__init__.py
sharp/codegen.py
sharp/error.py
sharp/function.py
sharp/js/class.js
sharp/js/function.js
sharp/naming/__init__.py
Flask_Sharp-0.0.7.dist-info/LICENSE
Flask_Sharp-0.0.7.dist-info/METADATA
Flask_Sharp-0.0.7.dist-info/WHEEL
Flask_Sharp-0.0.7.dist-info/top_level.txt
Flask_Sharp-0.0.7.dist-info/RECORD
