Metadata-Version: 2.1
Name: Flask-Sharp
Version: 0.0.7
Summary: An automatic code API generator for Flask and JS.
Home-page: https://github.com/revalo/sharp
Author: Shreyas Kapur
Author-email: sharp-dev@mit.edu
Maintainer: Shreyas Kapur
Maintainer-email: sharp-dev@mit.edu
License: MIT
Project-URL: Documentation, https://github.com/revalo/sharp/README.md
Project-URL: Code, https://github.com/revalo/sharp
Project-URL: Issue tracker, https://github.com/revalo/sharp/issues
Platform: UNKNOWN
Classifier: Development Status :: 3 - Alpha
Classifier: Environment :: Web Environment
Classifier: Framework :: Flask
Classifier: Intended Audience :: Developers
Classifier: License :: OSI Approved :: MIT License
Classifier: Operating System :: OS Independent
Classifier: Programming Language :: Python
Classifier: Topic :: Internet :: WWW/HTTP :: Dynamic Content
Classifier: Topic :: Internet :: WWW/HTTP :: WSGI
Classifier: Topic :: Internet :: WWW/HTTP :: WSGI :: Application
Classifier: Topic :: Software Development :: Libraries :: Application Frameworks
Requires-Python: >=3.6
Requires-Dist: Jinja2 (>=2.10.1)
Requires-Dist: typeguard (==2.9.1)
